{"hash": "3:v0lYqlC3jn:E0n", "head": 134359904, "tail": 134359934, "hcfg": {}, "acfg": {"cfg": {"0": ["1"], "1": ["2", "3"], "2": ["5"], "3": ["1", "4"], "4": ["5"], "5": []}, "hash": {"0": "3:u:u", "1": "3:E0:E0", "2": "3:e:e", "3": "3:cT5C1:d", "4": "3:c:c", "5": "3:y:y"}, "ea": {"0": [134359904, 134359908], "1": [134359908, 134359912], "2": [134359912, 134359916], "3": [134359916, 134359930], "4": [134359930, 134359932], "5": [134359932, 134359934]}, "attr": {"0": {"consts": [0], "symbol": [], "calls": 0, "insts": 3, "insts_list": ["PUSH", "MOVS", "CMP"]}, "1": {"consts": [0], "symbol": [], "calls": 0, "insts": 3, "insts_list": ["CMP", "BNE", "MOVS"], "equaled-jumps": 1}, "2": {"consts": [0], "symbol": [], "calls": 0, "insts": 3, "insts_list": ["MOVS", "B", "LDRB"], "flags-jumps": 1}, "3": {"consts": [1], "symbol": [], "calls": 0, "insts": 7, "insts_list": ["LDRB", "ADDS", "ADDS", "LDRB.W", "CMP", "BEQ", "SUBS"], "equaled-jumps": 1}, "4": {"consts": [], "symbol": [], "calls": 0, "insts": 2, "insts_list": ["SUBS", "POP"], "ret": 1}, "5": {"consts": [], "symbol": [], "calls": 0, "insts": 2, "insts_list": ["POP", "PUSH"], "ret": 1}}}}