{"hash": "6:Omuva2Fh1+flO9riV/99l0Hw19FVLDiV9ZH+Xn58kBg4mfYO/plY:OTb8NYGl0HA9FtiVnMCkdmfY+p2", "head": 32, "tail": 291, "hcfg": {}, "acfg": {"cfg": {"0": ["1", "13"], "1": ["2", "14"], "2": ["3", "11"], "3": ["4", "29"], "4": ["5", "14"], "5": ["6", "13"], "6": ["7", "29"], "7": ["8", "14"], "8": ["9", "13"], "9": ["10", "29"], "10": ["14"], "11": ["12", "13"], "12": ["11", "13"], "13": [], "14": ["16"], "15": ["16"], "16": ["17", "30"], "17": ["15", "18"], "18": ["19", "29"], "19": ["20", "29"], "20": ["21", "29"], "21": ["22", "29"], "22": ["24"], "23": ["24"], "24": ["25", "30"], "25": ["26", "29"], "26": ["27", "29"], "27": ["28", "29"], "28": ["23", "29"], "29": [], "30": ["31", "37"], "31": ["29", "32"], "32": ["33", "38"], "33": ["29", "34"], "34": ["35", "39"], "35": ["29", "36"], "36": [], "37": [], "38": [], "39": []}, "hash": {"0": "3:OmL:OmL", "1": "3:Y:Y", "2": "3:2:2", "3": "3:4an:4an", "4": "3:pTn:N", "5": "3:2J:2J", "6": "3:L:L", "7": "3:pAn:en", "8": "3:28:28", "9": "3:1:1", "10": "3:pjZ:NZ", "11": "3:2h:2h", "12": "3:pzZ:dZ", "13": "3:Wn:Wn", "14": "3:9ll:9ll", "15": "3:IuW:IuW", "16": "3:Sn:Sn", "17": "3:1m:4", "18": "3:ln:ln", "19": "3:otDn:wDn", "20": "3:0C3n:rn", "21": "3:nn:nn", "22": "3:Iuk/:Iuk/", "23": "3:Zn:Z", "24": "3:Jl:Jl", "25": "3:Cn:C", "26": "3:f:f", "27": "3:o:o", "28": "3:eN:eN", "29": "3:y:y", "30": "3:v:v", "31": "3:kn:k", "32": "3:0B:0B", "33": "3:pDn:pDn", "34": "3:kCn:kCn", "35": "3:K:K", "36": "3:AXQl2:A62", "37": "3:51VzdY:g", "38": "3:Bj+n:gn", "39": "3:41wlYn:41wlY"}, "ea": {"0": [32, 46], "1": [46, 52], "2": [52, 58], "3": [58, 63], "4": [63, 68], "5": [68, 79], "6": [79, 82], "7": [82, 87], "8": [87, 98], "9": [98, 101], "10": [101, 106], "11": [108, 119], "12": [119, 124], "13": [124, 129], "14": [132, 141], "15": [141, 145], "16": [145, 155], "17": [155, 161], "18": [161, 164], "19": [164, 173], "20": [173, 179], "21": [179, 182], "22": [182, 189], "23": [189, 191], "24": [191, 200], "25": [200, 203], "26": [203, 206], "27": [206, 209], "28": [209, 212], "29": [212, 216], "30": [216, 222], "31": [222, 228], "32": [228, 231], "33": [231, 237], "34": [237, 240], "35": [240, 243], "36": [243, 254], "37": [256, 267], "38": [268, 279], "39": [280, 291]}, "attr": {"0": {"insts": 6, "insts_list": ["entry", "l8ui", "l8ui", "movi", "bne", "or"], "equaled-jumps": 1, "logic": 1}, "1": {"insts": 3, "insts_list": ["or", "bnone", "xor"], "logic": 2, "flags-jumps": 1}, "2": {"insts": 3, "insts_list": ["xor", "bany", "addi"], "logic": 1, "flags-jumps": 1, "arithmetic": 1}, "3": {"insts": 3, "insts_list": ["addi", "beqz", "addi"], "arithmetic": 2, "flags-jumps": 1}, "4": {"insts": 3, "insts_list": ["addi", "bnone", "l8ui"], "arithmetic": 1, "flags-jumps": 1}, "5": {"insts": 5, "insts_list": ["l8ui", "l8ui", "addi", "bne", "beqz"], "arithmetic": 1, "equaled-jumps": 1, "flags-jumps": 1}, "6": {"insts": 2, "insts_list": ["beqz", "addi"], "flags-jumps": 1, "arithmetic": 1}, "7": {"insts": 3, "insts_list": ["addi", "bnone", "l8ui"], "arithmetic": 1, "flags-jumps": 1}, "8": {"insts": 5, "insts_list": ["l8ui", "l8ui", "addi", "bne", "beqz"], "arithmetic": 1, "equaled-jumps": 1, "flags-jumps": 1}, "9": {"insts": 2, "insts_list": ["beqz", "addi"], "flags-jumps": 1, "arithmetic": 1}, "10": {"insts": 3, "insts_list": ["addi", "j", ""], "arithmetic": 1, "flags-jumps": 1}, "11": {"insts": 5, "insts_list": ["l8ui", "l8ui", "addi", "bne", "addi"], "arithmetic": 2, "equaled-jumps": 1}, "12": {"insts": 3, "insts_list": ["addi", "bnez", "sub"], "arithmetic": 2, "flags-jumps": 1}, "13": {"insts": 3, "insts_list": ["sub", "retw", ""], "arithmetic": 1, "ret": 1}, "14": {"insts": 4, "insts_list": ["movi", "l32r", "j", "addi"], "flags-jumps": 1, "arithmetic": 1}, "15": {"insts": 3, "insts_list": ["addi", "addi", "l32i"], "arithmetic": 2}, "16": {"insts": 5, "insts_list": ["l32i", "l32i", "slli", "bne", "or"], "shift": 1, "equaled-jumps": 1, "logic": 1}, "17": {"insts": 3, "insts_list": ["or", "ball", "bnone"], "logic": 1, "flags-jumps": 2}, "18": {"insts": 2, "insts_list": ["bnone", "l32r"], "flags-jumps": 1}, "19": {"insts": 4, "insts_list": ["l32r", "l32r", "bnone", "l32r"], "flags-jumps": 1}, "20": {"insts": 3, "insts_list": ["l32r", "bnone", "bnone"], "flags-jumps": 2}, "21": {"insts": 2, "insts_list": ["bnone", "addi"], "flags-jumps": 1, "arithmetic": 1}, "22": {"insts": 4, "insts_list": ["addi", "addi", "j", "addi"], "arithmetic": 3, "flags-jumps": 1}, "23": {"insts": 2, "insts_list": ["addi", "l32i"], "arithmetic": 1}, "24": {"insts": 5, "insts_list": ["l32i", "l32i", "addi", "bne", "bnone"], "arithmetic": 1, "equaled-jumps": 1, "flags-jumps": 1}, "25": {"insts": 2, "insts_list": ["bnone", "bnone"], "flags-jumps": 2}, "26": {"insts": 2, "insts_list": ["bnone", "bnone"], "flags-jumps": 2}, "27": {"insts": 2, "insts_list": ["bnone", "bany"], "flags-jumps": 2}, "28": {"insts": 2, "insts_list": ["bany", "movi"], "flags-jumps": 1}, "29": {"insts": 3, "insts_list": ["movi", "retw", "xor"], "ret": 1, "logic": 1}, "30": {"insts": 3, "insts_list": ["xor", "bany", "l32r"], "logic": 1, "flags-jumps": 1}, "31": {"insts": 3, "insts_list": ["l32r", "bnone", "bany"], "flags-jumps": 2}, "32": {"insts": 2, "insts_list": ["bany", "l32r"], "flags-jumps": 1}, "33": {"insts": 3, "insts_list": ["l32r", "bnone", "bany"], "flags-jumps": 2}, "34": {"insts": 2, "insts_list": ["bany", "bnone"], "flags-jumps": 2}, "35": {"insts": 2, "insts_list": ["bnone", "extui"], "flags-jumps": 1, "shift": 1}, "36": {"insts": 5, "insts_list": ["extui", "extui", "sub", "retw", ""], "shift": 2, "arithmetic": 1, "ret": 1}, "37": {"insts": 5, "insts_list": ["extui", "extui", "sub", "retw", ""], "shift": 2, "arithmetic": 1, "ret": 1}, "38": {"insts": 5, "insts_list": ["extui", "extui", "sub", "retw", ""], "shift": 2, "arithmetic": 1, "ret": 1}, "39": {"insts": 5, "insts_list": ["extui", "extui", "sub", "retw", ""], "shift": 2, "arithmetic": 1, "ret": 1}}}}