{"hash": "3:P9z8mdjfTJ0m9DFOj6lk8dDfF:P58sfTJ0m9DFa6l1dbF", "head": 319744, "tail": 319836, "hcfg": {}, "acfg": {"cfg": {"0": []}, "hash": {"0": "3:P9z8mdjfTJ0m9DFOj6lk8dDfF:P58sfTJ0m9DFa6l1dbF"}, "ea": {"0": [319744, 319836]}, "attr": {"0": {"consts": [4180, 4180], "symbol": ["__syscall_cp", "__syscall_ret"], "calls": 2, "insts": 23, "insts_list": ["li", "addu", "addiu", "lw", "la", "sw", "lw", "sw", "sw", "sw", "sw", "move", "move", "move", "jalr", "li", "lw", "lw", "la", "move", "jr", "addiu", "jr"], "arithmetic": 3, "flags-jumps": 2}}}}