{"hash": "3:4//+1UwO:4u1UwO", "head": 1610621788, "tail": 1610621810, "hcfg": {}, "acfg": {"cfg": {"0": ["2"], "1": ["2"], "2": ["1", "3"], "3": []}, "hash": {"0": "3:4//n:4X", "1": "3:S:S", "2": "3:0pL:0p", "3": "3:n:n"}, "ea": {"0": [1610621788, 1610621796], "1": [1610621796, 1610621798], "2": [1610621798, 1610621806], "3": [1610621806, 1610621810]}, "attr": {"0": {"insts": 4, "insts_list": ["entry", "movi", "j", "addi"], "flags-jumps": 1, "arithmetic": 1}, "1": {"insts": 2, "insts_list": ["addi", "add"], "arithmetic": 2}, "2": {"insts": 4, "insts_list": ["add", "l8ui", "bnez", "mov"], "arithmetic": 1, "flags-jumps": 1}, "3": {"insts": 3, "insts_list": ["mov", "retw", ""], "ret": 1}}}}