{"hash": "6:6lxE4A7OSmaWxderuWR5YTEZrRBZ4/REHHY:6TyKxkpvYTEZrHZ4/SY", "head": 294752, "tail": 294988, "hcfg": {}, "acfg": {"cfg": {"0": ["1"], "1": ["2", "8"], "2": ["3"], "3": ["4", "3"], "4": ["5"], "5": ["6", "18"], "6": ["7", "11"], "7": [], "8": ["9"], "9": ["10", "18"], "10": ["1"], "11": ["12", "18"], "12": ["13", "14"], "13": [], "14": ["15", "18"], "15": ["16", "17"], "16": [], "17": ["3", "18"], "18": []}, "hash": {"0": "3:rn:r", "1": "3:X:X", "2": "3:qbhS4de7ndn:qE4A7d", "3": "3:ec5CnSm3XaWCnWdZiRb9avGn:ISmaWxdern", "4": "3:uSLlF:uWF", "5": "3:Glq:Gs", "6": "3:uTS1X:uTSV", "7": "3:Mk5:Mk5", "8": "3:n+lOF:BF", "9": "3:GlS:GU", "10": "3:MkVK:Mk0", "11": "3:Gli:Gk", "12": "3:uQZy:u7", "13": "3:Mnr/F:Mr/F", "14": "3:Gl+:G4", "15": "3:uRGT:uRc", "16": "3:Mmrlf:Mm5", "17": "3:Gls:Gi", "18": "3:FljF:B"}, "ea": {"0": [294752, 294756], "1": [294756, 294764], "2": [294764, 294788], "3": [294788, 294848], "4": [294848, 294860], "5": [294860, 294868], "6": [294868, 294880], "7": [294880, 294888], "8": [294888, 294900], "9": [294900, 294908], "10": [294908, 294916], "11": [294916, 294924], "12": [294924, 294936], "13": [294936, 294944], "14": [294944, 294952], "15": [294952, 294964], "16": [294964, 294972], "17": [294972, 294980], "18": [294980, 294988]}, "attr": {"0": {"insts": 2, "insts_list": ["clrlwi", "andi."]}, "1": {"insts": 3, "insts_list": ["andi.", "bne+", "clrlwi"]}, "2": {"insts": 7, "insts_list": ["clrlwi", "clrlslwi", "or", "mr", "slwi", "or", "mr"], "logic": 2}, "3": {"insts": 16, "insts_list": ["mr", "addi", "lwz", "xor", "addis", "addis", "addi", "addi", "xor", "xor", "and", "oris", "ori", "cmpwi", "beq-", "lbz"], "arithmetic": 5, "logic": 6}, "4": {"insts": 4, "insts_list": ["lbz", "cmplw", "beqlr", "cmpwi"]}, "5": {"insts": 3, "insts_list": ["cmpwi", "beq", "lbz"], "equaled-jumps": 1}, "6": {"insts": 4, "insts_list": ["lbz", "cmplw", "bne+", "addi"], "arithmetic": 1}, "7": {"insts": 3, "insts_list": ["addi", "blr", "lbz"], "arithmetic": 1, "ret": 1}, "8": {"insts": 4, "insts_list": ["lbz", "cmplw", "beqlr", "cmpwi"]}, "9": {"insts": 3, "insts_list": ["cmpwi", "beq", "addi"], "equaled-jumps": 1, "arithmetic": 1}, "10": {"insts": 3, "insts_list": ["addi", "b", "cmpwi"], "arithmetic": 1, "flags-jumps": 1}, "11": {"insts": 3, "insts_list": ["cmpwi", "beq", "lbz"], "equaled-jumps": 1}, "12": {"insts": 4, "insts_list": ["lbz", "cmplw", "bne+", "addi"], "arithmetic": 1}, "13": {"insts": 3, "insts_list": ["addi", "blr", "cmpwi"], "arithmetic": 1, "ret": 1}, "14": {"insts": 3, "insts_list": ["cmpwi", "beq", "lbz"], "equaled-jumps": 1}, "15": {"insts": 4, "insts_list": ["lbz", "cmplw", "bne+", "addi"], "arithmetic": 1}, "16": {"insts": 3, "insts_list": ["addi", "blr", "cmpwi"], "arithmetic": 1, "ret": 1}, "17": {"insts": 3, "insts_list": ["cmpwi", "bne", "li"], "equaled-jumps": 1}, "18": {"insts": 3, "insts_list": ["li", "blr", "addi"], "ret": 1, "arithmetic": 1}}}}