{"hash": "3:nnVShs4Go3kh0ldfF0vdGcaasn/ZkEttYybf/CM6KHCtXcMbWzGZ/Zun/F:ghs4GmqCfF08rP/aEqif/C3NqzO/Z6", "head": 390604, "tail": 390780, "hcfg": {}, "acfg": {"cfg": {"0": ["1"], "1": ["2", "9"], "2": ["3", "15"], "3": ["4", "8"], "4": ["5"], "5": ["6", "15"], "6": ["7"], "7": ["5"], "8": ["1"], "9": ["10", "15"], "10": ["4", "11"], "11": ["12"], "12": ["4", "13"], "13": ["4", "14"], "14": ["12"], "15": []}, "hash": {"0": "3:nnn:n", "1": "3:ls/:W/", "2": "3:29:a", "3": "3:nob:M", "4": "3:xM0n:G0", "5": "3:/ln:t", "6": "3:nhFn:hFn", "7": "3:MkVCn:Mk8", "8": "3:MknaaZ:MkaS", "9": "3:25:e", "10": "3:nRkEttYym:CEqp", "11": "3:Ktl/CM0:KX/CD", "12": "3:AB:AB", "13": "3:EXcMbWp:ENqp", "14": "3:MhCaZub:M0aZI", "15": "3:FljF:B"}, "ea": {"0": [390604, 390608], "1": [390608, 390620], "2": [390620, 390624], "3": [390624, 390636], "4": [390636, 390644], "5": [390644, 390648], "6": [390648, 390660], "7": [390660, 390668], "8": [390668, 390680], "9": [390680, 390684], "10": [390684, 390708], "11": [390708, 390728], "12": [390728, 390732], "13": [390732, 390760], "14": [390760, 390772], "15": [390772, 390780]}, "attr": {"0": {"insts": 2, "insts_list": ["clrlwi", "andi."]}, "1": {"insts": 4, "insts_list": ["andi.", "cmpwi", "beq", "beq"], "equaled-jumps": 2}, "2": {"insts": 2, "insts_list": ["beq", "lbz"], "equaled-jumps": 1}, "3": {"insts": 4, "insts_list": ["lbz", "cmpw", "bne+", "addi"], "arithmetic": 1}, "4": {"insts": 3, "insts_list": ["addi", "mtctr", "bdz"], "arithmetic": 1}, "5": {"insts": 2, "insts_list": ["bdz", "lbz"]}, "6": {"insts": 4, "insts_list": ["lbz", "cmpw", "beqlr", "addi"], "arithmetic": 1}, "7": {"insts": 3, "insts_list": ["addi", "b", "addi"], "arithmetic": 2, "flags-jumps": 1}, "8": {"insts": 4, "insts_list": ["addi", "addi", "b", "beq"], "arithmetic": 2, "flags-jumps": 1, "equaled-jumps": 1}, "9": {"insts": 2, "insts_list": ["beq", "lbz"], "equaled-jumps": 1}, "10": {"insts": 7, "insts_list": ["lbz", "lis", "ori", "mullw", "cmpw", "beq-", "srwi"], "logic": 1, "arithmetic": 1}, "11": {"insts": 6, "insts_list": ["srwi", "lis", "addi", "ori", "mtctr", "bdz"], "arithmetic": 1, "logic": 1}, "12": {"insts": 2, "insts_list": ["bdz", "lwz"]}, "13": {"insts": 8, "insts_list": ["lwz", "xor", "addis", "addi", "andc", "and.", "bne-", "addi"], "logic": 2, "arithmetic": 3}, "14": {"insts": 4, "insts_list": ["addi", "addi", "b", "li"], "arithmetic": 2, "flags-jumps": 1}, "15": {"insts": 3, "insts_list": ["li", "blr", "addi"], "ret": 1, "arithmetic": 1}}}}