{"hash": "3:OHlkV2BrABlp8thLyDNqwL/3/FHBPll3/LHtABnPlxhBEBMB9lC7sX/73KFYkhft:OHC2OTGQBLP/FHBPlhRAHxhBEK1Pcvft", "head": 353936, "tail": 354115, "hcfg": {}, "acfg": {"cfg": {"0": ["1", "2"], "1": ["2"], "2": ["3", "4"], "3": [], "4": []}, "hash": {"0": "3:OHlkV2BrABlp8thLS:OHC2OTGw", "1": "3:3lq0qwL/3/FHBPll3/X:1NBLP/FHBPlhX", "2": "3:TtABnPlxhBEBMB9lC7sX/73KFw:hAHxhBEK1Pcw", "3": "3:Kl/m:+/m", "4": "3:un:u"}, "ea": {"0": [353936, 353967], "1": [353967, 354022], "2": [354022, 354102], "3": [354102, 354110], "4": [354110, 354115]}, "attr": {"0": {"consts": [], "symbol": [], "calls": 0, "insts": 8, "insts_list": ["sub", "mov", "mov", "mov", "mov", "test", "jz", "movaps"], "arithmetic": 1, "logic": 1, "flags-jumps": 1}, "1": {"consts": [40, 40], "symbol": [], "calls": 1, "insts": 9, "insts_list": ["movaps", "movaps", "movaps", "movaps", "movaps", "movaps", "movaps", "movaps", "mov"]}, "2": {"consts": [40, 40, 0, 0], "symbol": [], "calls": 3, "insts": 16, "insts_list": ["mov", "mov", "xor", "lea", "xor", "mov", "mov", "lea", "mov", "mov", "mov", "call", "mov", "xor", "jnz", "add"], "logic": 3, "flags-jumps": 1, "arithmetic": 1}, "3": {"consts": [], "symbol": [], "calls": 0, "insts": 3, "insts_list": ["add", "retn", "call"], "arithmetic": 1, "ret": 1}, "4": {"consts": [], "symbol": [], "calls": 0, "insts": 2, "insts_list": ["call", ""]}}}}