{"hash": "6:dMxw+k6MynXk7pO5c9PX8RXgLUDj27paKelV+VY8lO6Ra5Wzcq4g8lhVpR1Q+rv8:2VMK8VZXCrf270K6VoYD50bShaGo0RW", "head": 4333788, "tail": 4334232, "hcfg": {}, "acfg": {"cfg": {"0": ["1"], "1": ["2", "1"], "2": ["1", "3"], "3": ["4", "18"], "4": ["5"], "5": ["6", "21"], "6": ["7", "25"], "7": ["8"], "8": ["9"], "9": ["10", "27"], "10": ["11"], "11": ["12", "33"], "12": ["13", "17"], "13": ["14", "32"], "14": ["15", "16"], "15": ["16", "32"], "16": ["17"], "17": ["9"], "18": ["19", "20"], "19": ["20"], "20": ["5"], "21": ["8", "22"], "22": ["8", "23"], "23": ["8", "24"], "24": ["8"], "25": ["24", "26"], "26": ["8"], "27": ["28", "33"], "28": ["29", "31"], "29": ["30"], "30": ["11"], "31": ["30"], "32": ["17"], "33": ["34", "36"], "34": ["35", "40"], "35": [], "36": ["37", "38"], "37": ["38"], "38": ["35", "39"], "39": ["40", "41"], "40": ["41"], "41": ["35"]}, "hash": {"0": "3:PFnMxw+k6fi:dMxw+k66", "1": "3:8mllNc9FtlJ:8mynXJ", "2": "3:On7p1:On7p1", "3": "3:ITa99uBv:L9m", "4": "3:yNzlvv:ezt", "5": "3:L:L", "6": "3:3hn:x", "7": "3:Yn:Yn", "8": "3:147L0lu0:1gL2", "9": "3:9EM:9", "10": "3:H2n:Wn", "11": "3:A8:A8", "12": "3:fY:g", "13": "3:f9:V", "14": "3:y:y", "15": "3:Z1:L", "16": "3:uxO:uE", "17": "3:Jhpaln:hal", "18": "3:h:h", "19": "3:yNzlJ:ezT", "20": "3:kEu:kJ", "21": "3:5V76+:C+", "22": "3:RN1:N", "23": "3:KWTf1:rZ", "24": "3:yl+6al:2+6u", "25": "3:KW5Jda1:r5W1", "26": "3:g:g", "27": "3:xXHw79Nn:5gN", "28": "3:cXxn:chn", "29": "3:v:v", "30": "3:Y:Y", "31": "3:XAln:XAln", "32": "3:MCrn:MCr", "33": "3:Xlqn:1i", "34": "3:6lQ+7vl1n:6lQ+rvn", "35": "3:RlRy/L7V:RfCt", "36": "3:ot:ot", "37": "3:u:u", "38": "3:/:/", "39": "3:ol:ol", "40": "3:Mv:Mv", "41": "3:R:R"}, "ea": {"0": [4333788, 4333816], "1": [4333816, 4333840], "2": [4333840, 4333852], "3": [4333852, 4333872], "4": [4333872, 4333884], "5": [4333884, 4333888], "6": [4333888, 4333896], "7": [4333896, 4333900], "8": [4333900, 4333932], "9": [4333932, 4333948], "10": [4333948, 4333952], "11": [4333952, 4333956], "12": [4333956, 4333964], "13": [4333964, 4333968], "14": [4333968, 4333972], "15": [4333972, 4333976], "16": [4333976, 4333988], "17": [4333988, 4334000], "18": [4334000, 4334008], "19": [4334008, 4334016], "20": [4334016, 4334024], "21": [4334024, 4334032], "22": [4334032, 4334040], "23": [4334040, 4334056], "24": [4334056, 4334072], "25": [4334072, 4334088], "26": [4334088, 4334096], "27": [4334096, 4334112], "28": [4334112, 4334124], "29": [4334124, 4334128], "30": [4334128, 4334136], "31": [4334136, 4334144], "32": [4334144, 4334152], "33": [4334152, 4334160], "34": [4334160, 4334180], "35": [4334180, 4334204], "36": [4334204, 4334208], "37": [4334208, 4334212], "38": [4334212, 4334216], "39": [4334216, 4334220], "40": [4334220, 4334224], "41": [4334224, 4334232]}, "attr": {"0": {"insts": 8, "insts_list": ["subi", "stw", "stw", "stw", "stw", "mov", "mov", "mov"], "arithmetic": 1}, "1": {"insts": 7, "insts_list": ["mov", "ldbu", "addi", "andi", "cmpeqi", "bne", "subi"], "arithmetic": 2, "logic": 1, "equaled-jumps": 1}, "2": {"insts": 4, "insts_list": ["subi", "cmpltui", "bne", "andi"], "arithmetic": 1, "equaled-jumps": 1, "logic": 1}, "3": {"insts": 6, "insts_list": ["andi", "xori", "subi", "cmpnei", "bne", "ldb"], "logic": 2, "arithmetic": 1, "equaled-jumps": 1}, "4": {"insts": 4, "insts_list": ["ldb", "addi", "movi", "bne"], "arithmetic": 1, "equaled-jumps": 1}, "5": {"insts": 2, "insts_list": ["bne", "cmpeqi"], "equaled-jumps": 1}, "6": {"insts": 3, "insts_list": ["cmpeqi", "bne", "movi"], "equaled-jumps": 1}, "7": {"insts": 2, "insts_list": ["movi", "movhi"]}, "8": {"insts": 9, "insts_list": ["movhi", "subi", "add", "divu", "mul", "mov", "mov", "sub", "andi"], "arithmetic": 5, "logic": 1}, "9": {"insts": 5, "insts_list": ["andi", "subi", "cmpgeui", "bne", "subi"], "logic": 1, "arithmetic": 2, "equaled-jumps": 1}, "10": {"insts": 2, "insts_list": ["subi", "bge"], "arithmetic": 1, "signed-jumps": 1}, "11": {"insts": 2, "insts_list": ["bge", "cmpeqi"], "signed-jumps": 1}, "12": {"insts": 3, "insts_list": ["cmpeqi", "bne", "bltu"], "equaled-jumps": 1, "unsigned-jumps": 1}, "13": {"insts": 2, "insts_list": ["bltu", "bne"], "unsigned-jumps": 1, "equaled-jumps": 1}, "14": {"insts": 2, "insts_list": ["bne", "blt"], "equaled-jumps": 1, "signed-jumps": 1}, "15": {"insts": 2, "insts_list": ["blt", "mul"], "signed-jumps": 1, "arithmetic": 1}, "16": {"insts": 4, "insts_list": ["mul", "movi", "add", "addi"], "arithmetic": 3}, "17": {"insts": 4, "insts_list": ["addi", "ldb", "br", "cmpnei"], "arithmetic": 1, "flags-jumps": 1}, "18": {"insts": 3, "insts_list": ["cmpnei", "bne", "ldb"], "equaled-jumps": 1}, "19": {"insts": 3, "insts_list": ["ldb", "addi", "mov"], "arithmetic": 1}, "20": {"insts": 3, "insts_list": ["mov", "br", "cmpnei"], "flags-jumps": 1}, "21": {"insts": 3, "insts_list": ["cmpnei", "bne", "cmpnei"], "equaled-jumps": 1}, "22": {"insts": 3, "insts_list": ["cmpnei", "bne", "ldbu"], "equaled-jumps": 1}, "23": {"insts": 5, "insts_list": ["ldbu", "andi", "cmpeqi", "beq", "ldb"], "logic": 1, "equaled-jumps": 1}, "24": {"insts": 5, "insts_list": ["ldb", "movi", "addi", "br", "ldbu"], "arithmetic": 1, "flags-jumps": 1}, "25": {"insts": 5, "insts_list": ["ldbu", "andi", "cmpnei", "beq", "movi"], "logic": 1, "equaled-jumps": 1}, "26": {"insts": 3, "insts_list": ["movi", "br", "ori"], "flags-jumps": 1, "logic": 1}, "27": {"insts": 5, "insts_list": ["ori", "subi", "cmpgeui", "bne", "subi"], "logic": 1, "arithmetic": 2, "equaled-jumps": 1}, "28": {"insts": 4, "insts_list": ["subi", "cmpgeui", "bne", "movi"], "arithmetic": 1, "equaled-jumps": 1}, "29": {"insts": 2, "insts_list": ["movi", "sub"], "arithmetic": 1}, "30": {"insts": 3, "insts_list": ["sub", "br", "movi"], "arithmetic": 1, "flags-jumps": 1}, "31": {"insts": 3, "insts_list": ["movi", "br", "movi"], "flags-jumps": 1}, "32": {"insts": 3, "insts_list": ["movi", "br", "cmpnei"], "flags-jumps": 1}, "33": {"insts": 3, "insts_list": ["cmpnei", "bne", "call"], "equaled-jumps": 1, "calls": 1}, "34": {"insts": 6, "insts_list": ["call", "movi", "stw", "mov", "bne", "ldw"], "calls": 1, "equaled-jumps": 1}, "35": {"insts": 7, "insts_list": ["ldw", "ldw", "ldw", "ldw", "addi", "ret", "beq"], "arithmetic": 1, "ret": 1, "equaled-jumps": 1}, "36": {"insts": 2, "insts_list": ["beq", "sub"], "equaled-jumps": 1, "arithmetic": 1}, "37": {"insts": 2, "insts_list": ["sub", "beq"], "arithmetic": 1, "equaled-jumps": 1}, "38": {"insts": 2, "insts_list": ["beq", "beq"], "equaled-jumps": 2}, "39": {"insts": 2, "insts_list": ["beq", "subi"], "equaled-jumps": 1, "arithmetic": 1}, "40": {"insts": 2, "insts_list": ["subi", "stw"], "arithmetic": 1}, "41": {"insts": 3, "insts_list": ["stw", "br", "subi"], "flags-jumps": 1, "arithmetic": 1}}}}