{"hash": "12:9a08lxgAkDmOHxZE2W6r/DpptgaiesAk9hkUE600ANB7d4SMlkLfSgpgL43s:kJkAkDbvEEhptoehkvkUEWY5d4RMSgpS", "head": 274628, "tail": 275316, "hcfg": {}, "acfg": {"cfg": {"0": ["1", "52"], "1": ["2"], "2": ["3", "11"], "3": ["4", "28"], "4": ["5", "20"], "5": ["6", "16"], "6": ["7", "13"], "7": ["8"], "8": ["9", "19"], "9": ["10", "47"], "10": ["22"], "11": ["2", "12"], "12": [], "13": ["14"], "14": ["8", "15"], "15": ["23"], "16": ["17", "48"], "17": ["18"], "18": ["14", "19"], "19": ["23"], "20": ["21", "47"], "21": ["22"], "22": ["18", "23"], "23": ["24"], "24": ["25", "51"], "25": ["26"], "26": ["27", "49"], "27": ["51"], "28": ["29", "42"], "29": ["30", "38"], "30": ["31", "35"], "31": ["32"], "32": ["33", "41"], "33": ["34", "46"], "34": ["44"], "35": ["36"], "36": ["32", "37"], "37": ["23"], "38": ["39", "48"], "39": ["40"], "40": ["36", "41"], "41": ["23"], "42": ["43", "46"], "43": ["44"], "44": ["40", "45"], "45": ["23"], "46": ["47"], "47": ["23", "48"], "48": ["24"], "49": ["26", "50"], "50": ["51"], "51": [], "52": ["53"], "53": ["54", "55"], "54": [], "55": ["53", "56"], "56": ["12"]}, "hash": {"0": "3:9CZO7:9aO7", "1": "3:9un:Mn", "2": "3:hZARMvlxn:hZAR8lxn", "3": "3:zHkdqHjkXx:rgD", "4": "3:C:C", "5": "3:dRn:dRn", "6": "3:Znrn:Znr", "7": "3:SDsd:SD8", "8": "3:MOAypKrn:lOn", "9": "3:Gr:i", "10": "3:zJ0x:Kx", "11": "3:AAlqkx:AAc4", "12": "3:VkYn:5", "13": "3:+j9n:+j9", "14": "3:JnEY6n:P6n", "15": "3:l:l", "16": "3:plx:F", "17": "3:ac:ac", "18": "3:MOIM:X", "19": "3:rFmm:rFD", "20": "3:Rr:Rr", "21": "3:aW0n:aW0", "22": "3:5Pn:5Pn", "23": "3:B5:T", "24": "3:5Q:O", "25": "3:kuIl2g3:Ftg3", "26": "3:PLslx:PM", "27": "3:dlx:x", "28": "3:3lFAeUFgr:3liet", "29": "3:z:z", "30": "3:Znlx:Znlx", "31": "3:QdAk9T:QdAk9T", "32": "3:fhOAlllcPr:9/sr", "33": "3:Yn:Y", "34": "3:zJmn:8", "35": "3:ol98n:498", "36": "3:vp/fpTselwn:x/fpw6wn", "37": "3:jayn:Fn", "38": "3:Tx:9", "39": "3:QfxuhGBSPn:QJB8", "40": "3:CRFLuaIlczMx:CRdubSMx", "41": "3:D1:D1", "42": "3:wan:wa", "43": "3:3u:3u", "44": "3:LXilH6VcD:G96Vg", "45": "3:f:f", "46": "3:LXilHn:G9n", "47": "3:PJ:R", "48": "3:yRy:yU", "49": "3:Ewzl0qax:ELx", "50": "3:VP:l", "51": "3:znY:zY", "52": "3:g3n:yn", "53": "3:Prlrn:Pxr", "54": "3:OY:OY", "55": "3:Ewzl0A6:Ez", "56": "3:8:8"}, "ea": {"0": [274628, 274644], "1": [274644, 274648], "2": [274648, 274668], "3": [274668, 274692], "4": [274692, 274700], "5": [274700, 274704], "6": [274704, 274712], "7": [274712, 274724], "8": [274724, 274740], "9": [274740, 274748], "10": [274748, 274760], "11": [274760, 274776], "12": [274776, 274784], "13": [274784, 274796], "14": [274796, 274812], "15": [274812, 274816], "16": [274816, 274824], "17": [274824, 274832], "18": [274832, 274848], "19": [274848, 274860], "20": [274860, 274876], "21": [274876, 274884], "22": [274884, 274900], "23": [274900, 274904], "24": [274904, 274912], "25": [274912, 274932], "26": [274932, 274940], "27": [274940, 274948], "28": [274948, 274972], "29": [274972, 274976], "30": [274976, 274984], "31": [274984, 275000], "32": [275000, 275028], "33": [275028, 275036], "34": [275036, 275048], "35": [275048, 275060], "36": [275060, 275088], "37": [275088, 275092], "38": [275092, 275100], "39": [275100, 275120], "40": [275120, 275148], "41": [275148, 275156], "42": [275156, 275172], "43": [275172, 275180], "44": [275180, 275208], "45": [275208, 275212], "46": [275212, 275224], "47": [275224, 275232], "48": [275232, 275240], "49": [275240, 275260], "50": [275260, 275264], "51": [275264, 275272], "52": [275272, 275276], "53": [275276, 275284], "54": [275284, 275292], "55": [275292, 275312], "56": [275312, 275316]}, "attr": {"0": {"consts": [15], "symbol": [], "calls": 0, "insts": 5, "insts_list": ["MOV", "MOV", "CMP", "B.LS", "ADD"], "arithmetic": 3}, "1": {"consts": [1], "symbol": [], "calls": 0, "insts": 2, "insts_list": ["ADD", "MOV"], "arithmetic": 2}, "2": {"consts": [1, 7, 0], "symbol": [], "calls": 0, "insts": 6, "insts_list": ["MOV", "SUB", "MOV", "TST", "B.NE", "STP"], "arithmetic": 3, "logic": 1}, "3": {"consts": [3, 3, 3, 7, 7, 0, 1], "symbol": [], "calls": 0, "insts": 7, "insts_list": ["STP", "LSR", "AND", "MOV", "ANDS", "B.NE", "CMP"], "shift": 1, "logic": 1, "arithmetic": 1}, "4": {"consts": [1], "symbol": [], "calls": 0, "insts": 3, "insts_list": ["CMP", "B.EQ", "CBZ"]}, "5": {"consts": [3], "symbol": [], "calls": 0, "insts": 2, "insts_list": ["CBZ", "CMP"]}, "6": {"consts": [3, 16], "symbol": [], "calls": 0, "insts": 3, "insts_list": ["CMP", "B.EQ", "LDR"]}, "7": {"consts": [16, 2, 2], "symbol": [], "calls": 0, "insts": 4, "insts_list": ["LDR", "ADD", "LDR", "CMP"], "arithmetic": 1}, "8": {"consts": [3, 24, 1, 4], "symbol": [], "calls": 0, "insts": 5, "insts_list": ["CMP", "LDR", "LDR", "B.NE", "SUBS"]}, "9": {"consts": [4, 32], "symbol": [], "calls": 0, "insts": 3, "insts_list": ["SUBS", "B.EQ", "ADD"], "arithmetic": 1}, "10": {"consts": [32, 4], "symbol": [], "calls": 0, "insts": 4, "insts_list": ["ADD", "ADD", "B", "LDRB"], "arithmetic": 2, "flags-jumps": 1}, "11": {"consts": [1], "symbol": [], "calls": 0, "insts": 5, "insts_list": ["LDRB", "LDRB", "SUBS", "B.EQ", "MOV"], "arithmetic": 1}, "12": {"consts": [8], "symbol": [], "calls": 0, "insts": 3, "insts_list": ["MOV", "RET", "LDR"], "arithmetic": 1}, "13": {"consts": [8], "symbol": [], "calls": 0, "insts": 4, "insts_list": ["LDR", "ADD", "LDR", "CMP"], "arithmetic": 1}, "14": {"consts": [2, 16], "symbol": [], "calls": 0, "insts": 5, "insts_list": ["CMP", "LDR", "LDR", "B.EQ", "B"], "flags-jumps": 1}, "15": {"consts": [7], "symbol": [], "calls": 0, "insts": 2, "insts_list": ["B", "CMP"], "flags-jumps": 1}, "16": {"consts": [7], "symbol": [], "calls": 0, "insts": 3, "insts_list": ["CMP", "B.LS", "LDR"]}, "17": {"consts": [], "symbol": [], "calls": 0, "insts": 3, "insts_list": ["LDR", "LDR", "CMP"]}, "18": {"consts": [1, 8], "symbol": [], "calls": 0, "insts": 5, "insts_list": ["CMP", "LDR", "LDR", "B.EQ", "MOV"], "arithmetic": 1}, "19": {"consts": [], "symbol": [], "calls": 0, "insts": 4, "insts_list": ["MOV", "MOV", "B", "SUBS"], "arithmetic": 2, "flags-jumps": 1}, "20": {"consts": [8], "symbol": [], "calls": 0, "insts": 5, "insts_list": ["SUBS", "LDR", "LDR", "B.EQ", "ADD"], "arithmetic": 1}, "21": {"consts": [8], "symbol": [], "calls": 0, "insts": 3, "insts_list": ["ADD", "ADD", "CMP"], "arithmetic": 2}, "22": {"consts": [], "symbol": ["memcmp_bytes"], "calls": 1, "insts": 5, "insts_list": ["CMP", "LDR", "LDR", "B.EQ", "BL"]}, "23": {"consts": [], "symbol": ["memcmp_bytes"], "calls": 1, "insts": 2, "insts_list": ["BL", "SXTW"]}, "24": {"consts": [18446744073709551608, 18446744073709551608], "symbol": [], "calls": 0, "insts": 3, "insts_list": ["SXTW", "CBNZ", "AND"], "logic": 1}, "25": {"consts": [18446744073709551608, 18446744073709551608, 7, 0], "symbol": [], "calls": 0, "insts": 6, "insts_list": ["AND", "AND", "ADD", "ADD", "MOV", "CMP"], "logic": 2, "arithmetic": 3}, "26": {"consts": [0], "symbol": [], "calls": 0, "insts": 3, "insts_list": ["CMP", "B.NE", "MOV"], "arithmetic": 1}, "27": {"consts": [0, 8, 8], "symbol": [], "calls": 0, "insts": 3, "insts_list": ["MOV", "B", "LSL"], "arithmetic": 1, "flags-jumps": 1, "shift": 1}, "28": {"consts": [8, 8, 64, 18446744073709551608, 1], "symbol": [], "calls": 0, "insts": 7, "insts_list": ["LSL", "MOV", "AND", "SUB", "CMP", "B.EQ", "CBZ"], "shift": 1, "arithmetic": 2, "logic": 1}, "29": {"consts": [3], "symbol": [], "calls": 0, "insts": 2, "insts_list": ["CBZ", "CMP"]}, "30": {"consts": [3, 2], "symbol": [], "calls": 0, "insts": 3, "insts_list": ["CMP", "B.EQ", "LDR"]}, "31": {"consts": [2, 2, 1], "symbol": [], "calls": 0, "insts": 5, "insts_list": ["LDR", "ADD", "LDP", "SUB", "LSR"], "arithmetic": 2, "shift": 1}, "32": {"consts": [3, 3, 1, 4], "symbol": [], "calls": 0, "insts": 8, "insts_list": ["LSR", "LSL", "ORR", "CMP", "LDR", "LDR", "B.NE", "SUBS"], "shift": 2, "logic": 1}, "33": {"consts": [4, 4], "symbol": [], "calls": 0, "insts": 3, "insts_list": ["SUBS", "B.EQ", "ADD"], "arithmetic": 1}, "34": {"consts": [4, 4, 1], "symbol": [], "calls": 0, "insts": 4, "insts_list": ["ADD", "ADD", "B", "LDP"], "arithmetic": 2, "flags-jumps": 1}, "35": {"consts": [1], "symbol": [], "calls": 0, "insts": 4, "insts_list": ["LDP", "ADD", "LDR", "LSR"], "arithmetic": 1, "shift": 1}, "36": {"consts": [2, 2], "symbol": [], "calls": 0, "insts": 8, "insts_list": ["LSR", "LSL", "ORR", "CMP", "LDR", "LDR", "B.EQ", "B"], "shift": 2, "logic": 1, "flags-jumps": 1}, "37": {"consts": [7], "symbol": [], "calls": 0, "insts": 2, "insts_list": ["B", "CMP"], "flags-jumps": 1}, "38": {"consts": [7], "symbol": [], "calls": 0, "insts": 3, "insts_list": ["CMP", "B.LS", "MOV"], "arithmetic": 1}, "39": {"consts": [1], "symbol": [], "calls": 0, "insts": 6, "insts_list": ["MOV", "LDR", "LDR", "LDR", "MOV", "LSR"], "arithmetic": 2, "shift": 1}, "40": {"consts": [1, 1], "symbol": [], "calls": 0, "insts": 8, "insts_list": ["LSR", "LSL", "ORR", "CMP", "LDR", "LDR", "B.EQ", "MOV"], "shift": 2, "logic": 1, "arithmetic": 1}, "41": {"consts": [], "symbol": [], "calls": 0, "insts": 3, "insts_list": ["MOV", "B", "SUBS"], "arithmetic": 1, "flags-jumps": 1}, "42": {"consts": [1, 2], "symbol": [], "calls": 0, "insts": 5, "insts_list": ["SUBS", "LDR", "LDP", "B.EQ", "ADD"], "arithmetic": 1}, "43": {"consts": [2], "symbol": [], "calls": 0, "insts": 3, "insts_list": ["ADD", "ADD", "LSR"], "arithmetic": 2, "shift": 1}, "44": {"consts": [], "symbol": [], "calls": 0, "insts": 8, "insts_list": ["LSR", "LSL", "ORR", "CMP", "LDR", "LDR", "B.EQ", "B"], "shift": 2, "logic": 1, "flags-jumps": 1}, "45": {"consts": [], "symbol": [], "calls": 0, "insts": 2, "insts_list": ["B", "LSR"], "flags-jumps": 1, "shift": 1}, "46": {"consts": [], "symbol": [], "calls": 0, "insts": 4, "insts_list": ["LSR", "LSL", "ORR", "CMP"], "shift": 2, "logic": 1}, "47": {"consts": [0], "symbol": [], "calls": 0, "insts": 3, "insts_list": ["CMP", "B.NE", "MOV"], "arithmetic": 1}, "48": {"consts": [0], "symbol": [], "calls": 0, "insts": 3, "insts_list": ["MOV", "B", "LDRB"], "arithmetic": 1, "flags-jumps": 1}, "49": {"consts": [], "symbol": [], "calls": 0, "insts": 6, "insts_list": ["LDRB", "LDRB", "ADD", "SUBS", "B.EQ", "MOV"], "arithmetic": 2}, "50": {"consts": [], "symbol": [], "calls": 0, "insts": 2, "insts_list": ["MOV", "LDP"], "arithmetic": 1}, "51": {"consts": [0], "symbol": [], "calls": 0, "insts": 3, "insts_list": ["LDP", "RET", "MOV"], "arithmetic": 1}, "52": {"consts": [0], "symbol": [], "calls": 0, "insts": 2, "insts_list": ["MOV", "CMP"], "arithmetic": 1}, "53": {"consts": [0], "symbol": [], "calls": 0, "insts": 3, "insts_list": ["CMP", "B.NE", "MOV"], "arithmetic": 1}, "54": {"consts": [0], "symbol": [], "calls": 0, "insts": 3, "insts_list": ["MOV", "RET", "LDRB"], "arithmetic": 1}, "55": {"consts": [], "symbol": [], "calls": 0, "insts": 6, "insts_list": ["LDRB", "LDRB", "ADD", "SUBS", "B.EQ", "B"], "arithmetic": 1, "flags-jumps": 1}, "56": {"consts": [], "symbol": [], "calls": 0, "insts": 2, "insts_list": ["B", "MOV"], "flags-jumps": 1, "arithmetic": 1}}}}