{"hash": "3:6cEF3FTqm8CAXl0P0hA1D6aJ8vo2vn:6cEF3dqmAGP0h1roK", "head": 451364, "tail": 451448, "hcfg": {}, "acfg": {"cfg": {"0": []}, "hash": {"0": "3:6cEF3FTqm8CAXl0P0hA1D6aJ8vo2vn:6cEF3dqmAGP0h1roK"}, "ea": {"0": [451364, 451448]}, "attr": {"0": {"consts": [], "symbol": ["strlen", "strcpy"], "calls": 2, "insts": 21, "insts_list": ["li", "addu", "addiu", "la", "sw", "sw", "sw", "sw", "bal", "move", "lw", "lw", "la", "bal", "addu", "lw", "move", "lw", "jr", "addiu", "li"], "arithmetic": 4, "flags-jumps": 3}}}}