{"hash": "3:QAgqBaa9m7cBXFicsWJJn:QAgqBR9ScBX0csWJJn", "head": 458352, "tail": 458400, "hcfg": {}, "acfg": {"cfg": {"0": ["1"], "1": ["2", "3"], "2": [], "3": ["1"]}, "hash": {"0": "3:QAgqBn:QAgqBn", "1": "3:R9ScBn:7ScBn", "2": "3:Vmtl:Mtl", "3": "3:ysWJJn:ysWJJn"}, "ea": {"0": [458352, 458364], "1": [458364, 458376], "2": [458376, 458384], "3": [458384, 458400]}, "attr": {"0": {"consts": [18446744073709551615], "symbol": [], "calls": 0, "insts": 4, "insts_list": ["move", "move", "li", "addiu"], "arithmetic": 1}, "1": {"consts": [4], "symbol": [], "calls": 0, "insts": 4, "insts_list": ["addiu", "bne", "addiu", "jr"], "arithmetic": 2, "equaled-jumps": 1, "flags-jumps": 1}, "2": {"consts": [], "symbol": [], "calls": 0, "insts": 3, "insts_list": ["jr", "nop", "lw"], "flags-jumps": 1}, "3": {"consts": [4], "symbol": [], "calls": 0, "insts": 5, "insts_list": ["lw", "addiu", "b", "sw", "beq"], "arithmetic": 1, "flags-jumps": 1, "equaled-jumps": 1}}}}